{"_type":"export","__export_format":4,"__export_date":"2024-10-16T02:48:56.270Z","__export_source":"insomnia.desktop.app:v10.0.0","resources":[{"_id":"req_6fc12a9474ba4e5abfefc87a7d45df16","parentId":"fld_23fa403f0fee4c03b3cea1fbb804f67e","modified":1729029778765,"created":1728828160648,"url":"http://localhost:8000/api/v1/upload/save","name":"Upload","description":"## Endpoint para envio dos arquivos.\n### Method: POST\n##### URL: http://localhost:8000/api/v1/upload/save\n\n### Autenticação obrigatória\n#### O arquivo deve ter um tamanho máximo de 30MB\n#### Extensões permitidas csv, xls e xlsx\n### Campos obrigatórios\n- fileUpload (form data)\n\n```response:201\n{\n\t\"data\": {\n\t\t\"name\": \"InstrumentsConsolidatedFile_20241011_1.csv\",\n\t\t\"date\": \"2024-10-11T00:00:00.000000Z\",\n\t\t\"path\": \"https://desafioot.s3.amazonaws.com/InstrumentsConsolidatedFile_20241011_1.csv\",\n\t\t\"size\": 18640845,\n\t\t\"type\": \"text/plain\",\n\t\t\"processed\": false,\n\t\t\"updated_at\": \"2024-10-15T02:42:49.274000Z\",\n\t\t\"created_at\": \"2024-10-15T02:42:49.274000Z\",\n\t\t\"_id\": \"670dd6a9b62293604500d743\"\n\t},\n\t\"status\": 201\n}\n```\n```response:400\n{\n\t\"message\": \"File already exists\",\n\t\"status\": 400\n}\n``` \n","method":"POST","body":{"mimeType":"multipart/form-data","params":[{"id":"pair_6f70aaebf3194c38a650661351ff343b","name":"fileUpload","value":"","description":"","disabled":false,"type":"file","fileName":"/home/gustavo/Downloads/InstrumentsConsolidatedFile_20241011_1.csv"}]},"parameters":[],"headers":[{"name":"Content-Type","value":"multipart/form-data"},{"name":"User-Agent","value":"insomnia/10.0.0"}],"authentication":{"type":"bearer","token":"670d93da25ccc66a31034322|v4F016eHPtpznlO0Vok5T3BOJKFX3HIqdUXaEMg5f3fae05c"},"metaSortKey":-1728999326601,"isPrivate":false,"pathParameters":[],"settingStoreCookies":true,"settingSendCookies":true,"settingDisableRenderRequestBody":false,"settingEncodeUrl":true,"settingRebuildPath":true,"settingFollowRedirects":"global","_type":"request"},{"_id":"fld_23fa403f0fee4c03b3cea1fbb804f67e","parentId":"wrk_c9490d1360234b55bcf4caa998e8c720","modified":1728999315740,"created":1728999315740,"name":"Arquivo Upload","description":"","environment":{},"environmentPropertyOrder":null,"metaSortKey":-1728999315740,"_type":"request_group"},{"_id":"wrk_c9490d1360234b55bcf4caa998e8c720","parentId":null,"modified":1728828151918,"created":1728828151918,"name":"Desafio Oliveira","description":"","scope":"collection","_type":"workspace"},{"_id":"req_c432621f53384ebb9ff544477f178d0d","parentId":"fld_23fa403f0fee4c03b3cea1fbb804f67e","modified":1729030115378,"created":1728929530637,"url":"http://localhost:8000/api/v1/upload/log","name":"Histórico","description":"## Endpoint para consultar histórico dos arquivos enviados.\n### Method: POST\n##### URL: http://localhost:8000/api/v1/upload/log\n##### OBS.\n### Porque POST???\nDe acordo com a documentação e a especificação XMLHttpRequest ignora o corpo da solicitação caso o método seja GET. Se você realizar uma solicitação no Chrome/Electron com XMLHttpRequest e tentar colocar um corpo json no método send, isso será ignorado.\nNão queria passar via parâmetro na URL, usando method post fica melhor para validar.\n\n### Autenticação obrigatória\n\n### Campos possiveis (não obrigatórios)\n- name (string)\n- date (data format Y-m-d)\n\n```response:201\n{\n\t\"data\": [\n\t\t{\n\t\t\t\"_id\": \"670d5ed52d6da3b1700149ad\",\n\t\t\t\"name\": \"InstrumentsConsolidatedFile_20241010_1.csv\",\n\t\t\t\"date\": \"2024-10-14T00:00:00.000000Z\",\n\t\t\t\"path\": \"https://desafioot.s3.amazonaws.com/InstrumentsConsolidatedFile_20241010_1.csv\",\n\t\t\t\"size\": 18471128,\n\t\t\t\"type\": \"text/plain\",\n\t\t\t\"processed\": true\n\t\t},\n\t\t{\n\t\t\t\"_id\": \"670dd6a9b62293604500d743\",\n\t\t\t\"name\": \"InstrumentsConsolidatedFile_20241011_1.csv\",\n\t\t\t\"date\": \"2024-10-11T00:00:00.000000Z\",\n\t\t\t\"path\": \"https://desafioot.s3.amazonaws.com/InstrumentsConsolidatedFile_20241011_1.csv\",\n\t\t\t\"size\": 18640845,\n\t\t\t\"type\": \"text/plain\",\n\t\t\t\"processed\": true\n\t\t}\n\t],\n\t\"status\": 200\n}\n```\n```response:401\n{\n\t\"message\": \"File already exists\",\n\t\"status\": 400\n}\n``` ","method":"POST","body":{"mimeType":"application/json","text":"{\n\t\"name\": \"\",\n\t\"date\": \"\"\n}"},"parameters":[],"headers":[{"name":"Content-Type","value":"application/json","id":"pair_079b52b539b84c96ad13e48d56da7d1d"}],"authentication":{"type":"bearer","token":"670d93da25ccc66a31034322|v4F016eHPtpznlO0Vok5T3BOJKFX3HIqdUXaEMg5f3fae05c"},"metaSortKey":-1728999326551,"isPrivate":false,"pathParameters":[],"settingStoreCookies":true,"settingSendCookies":true,"settingDisableRenderRequestBody":false,"settingEncodeUrl":true,"settingRebuildPath":true,"settingFollowRedirects":"global","_type":"request"},{"_id":"req_13fd08928aae43fb851f2b0a942bc0b1","parentId":"fld_23fa403f0fee4c03b3cea1fbb804f67e","modified":1729012584515,"created":1728930594439,"url":"http://localhost:8000/api/v1/upload/getData?TckrSymb=A1LG34R&RptDt=","name":"Consulta dados","description":"## Endpoint para consultar dados dos arquivos enviados.\n### Method: GET\n##### URL: http://localhost:8000/api/v1/upload/getData?TckrSymb=A1LG34R&RptDt=\n\n### Autenticação obrigatória\n\n### Parâmetros possiveis (não obrigatórios)\n- TckrSymb (string)\n- RptDt (data format Y-m-d)\n\n```response:201\n{\n\t\"data\": [\n\t\t{\n\t\t\t\"RptDt\": \"2024-10-10T00:00:00.000000Z\",\n\t\t\t\"TckrSymb\": \"A1LG34R\",\n\t\t\t\"MktNm\": \"EQUITY-CASH\",\n\t\t\t\"SctyCtgyNm\": \"BDR\",\n\t\t\t\"ISIN\": \"BRA1LGBDR007\",\n\t\t\t\"CrpnNm\": \"ALIGN TECHNOLOGY INC\"\n\t\t},\n\t\t{\n\t\t\t\"RptDt\": \"2024-10-11T00:00:00.000000Z\",\n\t\t\t\"TckrSymb\": \"A1LG34R\",\n\t\t\t\"MktNm\": \"EQUITY-CASH\",\n\t\t\t\"SctyCtgyNm\": \"BDR\",\n\t\t\t\"ISIN\": \"BRA1LGBDR007\",\n\t\t\t\"CrpnNm\": \"ALIGN TECHNOLOGY INC\"\n\t\t}\n\t],\n\t\"status\": 200\n}\n```\n```response:400\n{\n\t\"message\": \"File already exists\",\n\t\"status\": 400\n}\n``` ","method":"GET","body":{},"parameters":[],"headers":[{"id":"pair_50506d9ef38b437faa718070bb877e38","name":"Content-Type","value":"application/json","description":"","disabled":false}],"authentication":{"type":"bearer","token":"670d93da25ccc66a31034322|v4F016eHPtpznlO0Vok5T3BOJKFX3HIqdUXaEMg5f3fae05c"},"metaSortKey":-1728999326526,"isPrivate":false,"pathParameters":[],"settingStoreCookies":true,"settingSendCookies":true,"settingDisableRenderRequestBody":false,"settingEncodeUrl":true,"settingRebuildPath":true,"settingFollowRedirects":"global","_type":"request"},{"_id":"req_06333ac641464071b3d9f63b32eac4a1","parentId":"fld_23fa403f0fee4c03b3cea1fbb804f67e","modified":1729046883984,"created":1728937874673,"url":"http://localhost:8000/api/v1/upload/delete/670eeced2648ac80280f0f73","name":"Delete","description":"## Endpoint para deletar arquivos enviados.\n### Method: DELETE\n##### URL: http://localhost:8000/api/v1/upload/delete/{file _id}\n\n### Autenticação obrigatória\n\n### Parâmetros possiveis (obrigatório)\n- _id (string)\n\n```response:204\n{\n\tNo data\n}\n```\n```response:404\n{\n\t\"message\": \"File not found\",\n\t\"status\": 404\n}\n``` ","method":"DELETE","body":{},"parameters":[],"headers":[{"id":"pair_9db36e5188aa4b10ac738153eb571a4d","name":"Content-Type","value":"application/json","description":"","disabled":false}],"authentication":{"type":"bearer","token":"670d93da25ccc66a31034322|v4F016eHPtpznlO0Vok5T3BOJKFX3HIqdUXaEMg5f3fae05c","disabled":false},"metaSortKey":-1728999326501,"isPrivate":false,"pathParameters":[],"settingStoreCookies":true,"settingSendCookies":true,"settingDisableRenderRequestBody":false,"settingEncodeUrl":true,"settingRebuildPath":true,"settingFollowRedirects":"global","_type":"request"},{"_id":"req_757302e85cdf41e6b1c1e042d1ae5ee2","parentId":"fld_a2ab226946854f8b8057711db4c6a1a1","modified":1729007624869,"created":1728940434640,"url":"http://localhost:8000/api/v1/user/create","name":"Create User","description":"## Endpoint para cadastro de usuários.\n### Method: POST\n##### URL: http://localhost:8000/api/v1/user/create\n\n### Autenticação NÃO obrigatória\n\n### Campos obrigatórios\n- name (string)\n- email (string email format)\n- password (string max 8 caracteres)\n\n```response:201\n{\n\t\"data\": {\n\t\t\"name\": \"Gustavo Villela Goulart\",\n\t\t\"email\": \"gvillela7@gmail.com\",\n\t\t\"updated_at\": \"2024-10-14T21:25:21.095000Z\",\n\t\t\"created_at\": \"2024-10-14T21:25:21.095000Z\",\n\t\t\"_id\": \"670d8c41bba49171cd078df2\"\n\t},\n\t\"status\": 201\n}\n```\n```response:400\n{\n\t\"success\": false,\n\t\"statusCode\": 400,\n\t\"message\": \"Validation errors\",\n\t\"data\": {\n\t\t\"email\": [\n\t\t\t\"The email field must be a valid email address.\"\n\t\t]\n\t}\n}\n``` \n","method":"POST","body":{"mimeType":"application/json","text":"{\n\t\"name\": \"Gustavo Villela Goulart\",\n\t\"email\": \"gvillela7gmail.com\",\n\t\"password\": \"1q2w3e4r\"\n}"},"parameters":[],"headers":[{"name":"Content-Type","value":"application/json","id":"pair_19158d48bf2449099c0f5a74d73a9727"}],"authentication":{},"metaSortKey":-1728940434640,"isPrivate":false,"pathParameters":[],"settingStoreCookies":true,"settingSendCookies":true,"settingDisableRenderRequestBody":false,"settingEncodeUrl":true,"settingRebuildPath":true,"settingFollowRedirects":"global","_type":"request"},{"_id":"fld_a2ab226946854f8b8057711db4c6a1a1","parentId":"wrk_c9490d1360234b55bcf4caa998e8c720","modified":1728940425248,"created":1728940425248,"name":"User","description":"","environment":{},"environmentPropertyOrder":null,"metaSortKey":-1728940425248,"_type":"request_group"},{"_id":"req_3929f0a4ccf54abbb8760074edc788d2","parentId":"fld_a2ab226946854f8b8057711db4c6a1a1","modified":1729007647063,"created":1728941541554,"url":"http://localhost:8000/api/v1/user/login","name":"Login","description":"## Endpoint para autenticação de usuários.\n### Method: POST\n##### URL: http://localhost:8000/api/v1/user/login\n\n### Autenticação NÃO obrigatória\n\n### Campos obrigatórios\n- email (string email format)\n- password (string max 8 caracteres)\n\n```response:200\n{\n\t\"access_token\": \"670d93da25ccc66a31034322|v4F016eHPtpznlO0Vok5T3BOJKFX3HIqdUXaEMg5f3fae05c\",\n\t\"status\": 200\n}\n```\n```response:401\n{\n\t\"message\": \"Invalid Credentials\",\n\t\"status\": 401\n}\n``` \n","method":"POST","body":{"mimeType":"application/json","text":"{\n\t\"email\": \"gvillela7@gmail.com\",\n\t\"password\": \"1q2w3e\"\n}"},"parameters":[],"headers":[{"name":"Content-Type","value":"application/json","id":"pair_c149365c06f748ccadf45b0e700f3d12"}],"authentication":{},"metaSortKey":-1728935514539.5,"isPrivate":false,"pathParameters":[],"settingStoreCookies":true,"settingSendCookies":true,"settingDisableRenderRequestBody":false,"settingEncodeUrl":true,"settingRebuildPath":true,"settingFollowRedirects":"global","_type":"request"},{"_id":"env_65440d8e060e30f4cf507452fbd4d99e1ca6a922","parentId":"wrk_c9490d1360234b55bcf4caa998e8c720","modified":1728828151939,"created":1728828151939,"name":"Base Environment","data":{},"dataPropertyOrder":null,"color":null,"isPrivate":false,"metaSortKey":1728828151939,"_type":"environment"},{"_id":"jar_65440d8e060e30f4cf507452fbd4d99e1ca6a922","parentId":"wrk_c9490d1360234b55bcf4caa998e8c720","modified":1728828151940,"created":1728828151940,"name":"Default Jar","cookies":[],"_type":"cookie_jar"}]}